rust_python_jaeger_reporter-0.1.23.dist-info/METADATA
rust_python_jaeger_reporter-0.1.23.dist-info/WHEEL
rust_python_jaeger_reporter/__init__.py
rust_python_jaeger_reporter/rust_python_jaeger_reporter.cpython-38-x86_64-linux-gnu.so
rust_python_jaeger_reporter-0.1.23.dist-info/RECORD
