Metadata-Version: 2.3
Name: rust-python-jaeger-reporter
Version: 0.1.23
Summary: A faster reporter for the python `jaeger-client` that reports spans in a native background thread.
Author: Erik Johnston <erik@matrix.org>
Author-email: Erik Johnston <erik@matrix.org>
Requires-Python: >=3.7
Project-URL: Source, https://github.com/erikjohnston/rust-jaeger-python-client
